findall/__init__.py
findall-1.0.0.dist-info/METADATA
findall-1.0.0.dist-info/WHEEL
findall-1.0.0.dist-info/top_level.txt
findall-1.0.0.dist-info/RECORD
